asynchronizer/__init__.py
asynchronizer/_tasks.py
asynchronizer/thread.py
asynchronizer/utils.py
pysynchronizer-1.0.dist-info/LICENSE
pysynchronizer-1.0.dist-info/METADATA
pysynchronizer-1.0.dist-info/WHEEL
pysynchronizer-1.0.dist-info/top_level.txt
pysynchronizer-1.0.dist-info/RECORD
