Metadata-Version: 2.1
Name: pysynchronizer
Version: 1.0
Summary: A class or decorator to help with asynchronous programming in Python within synchronous contexts.
Author-email: John Gaddis <normlman@live.com>
Project-URL: Homepage, https://github.com/irjohn/asynchronizer
Classifier: Programming Language :: Python :: 3
Classifier: License :: OSI Approved :: GNU General Public License v3 or later (GPLv3+)
Classifier: Operating System :: OS Independent
Requires-Python: >=3.7
License-File: LICENSE
